{
  "required": true,
  "minVersion": "0.8",
  "package": "org.example.sansrus.sansrusmod.client.mixin",
  "compatibilityLevel": "JAVA_21",
  "client": [
    "ChatHudMixin",
    "DisableRmbCooldownMixin",
    "HandledScreenMixin",
    "VillagerProtectMixin",
    "armorbar.ArmorBarHudMixin",
    "book.BookEditScreenMixin",
    "book.BookScreenMixin",
    "chat.ChatMessageCounterMixin",
    "chatcoord.ChatCoordParserMixin",
    "cyrilliccommands.ChatInputSuggestorMixin",
    "cyrilliccommands.ChatScreenMixin",
    "deathlog.InventoryScreenMixin",
    "elytrafeature.CapeFeatureRendererMixin",
    "elytrafeature.ElytraFeatureRendererMixin",
    "highlight.MatchingSlotHighlightMixin",
    "nauseafix.NauseaOverlayFixMixin"
  ],
  "injectors": {
    "defaultRequire": 1
  },
  "overwrites": {
    "requireAnnotations": true
  },
  "mixins": [
    "EntityMixin",
    "ItemStackTooltipMixin",
    "deathlog.DeathInventoryCaptureMixin",
    "maptip.ItemStackMapTooltipMixin"
  ]
}
